AUTHORS
CHANGELOG
INSTALL
LICENSE
MANIFEST.in
README
VERSION
setup.cfg
setup.py
django_formrenderingtools.egg-info/PKG-INFO
django_formrenderingtools.egg-info/SOURCES.txt
django_formrenderingtools.egg-info/dependency_links.txt
django_formrenderingtools.egg-info/namespace_packages.txt
django_formrenderingtools.egg-info/not-zip-safe
django_formrenderingtools.egg-info/requires.txt
django_formrenderingtools.egg-info/top_level.txt
djc/__init__.py
djc/formrenderingtools/__init__.py
djc/formrenderingtools/models.py
djc/formrenderingtools/settings.py
djc/formrenderingtools/tests.py
djc/formrenderingtools/templates/form_layouts/as_p/field/default.html
djc/formrenderingtools/templates/form_layouts/as_p/form_errors/default.html
djc/formrenderingtools/templates/form_layouts/as_p/help_text/default.html
djc/formrenderingtools/templates/form_layouts/as_p/label/default.html
djc/formrenderingtools/templates/form_layouts/as_table/field/default.html
djc/formrenderingtools/templates/form_layouts/as_table/form_errors/default.html
djc/formrenderingtools/templates/form_layouts/as_table/help_text/default.html
djc/formrenderingtools/templates/form_layouts/as_table/label/default.html
djc/formrenderingtools/templates/form_layouts/as_ul/field/default.html
djc/formrenderingtools/templates/form_layouts/as_ul/form_errors/default.html
djc/formrenderingtools/templates/form_layouts/as_ul/help_text/default.html
djc/formrenderingtools/templates/form_layouts/as_ul/label/default.html
djc/formrenderingtools/templates/form_layouts/default/field/default.html
djc/formrenderingtools/templates/form_layouts/default/field_errors/default.html
djc/formrenderingtools/templates/form_layouts/default/field_list/default.html
djc/formrenderingtools/templates/form_layouts/default/form/default.html
djc/formrenderingtools/templates/form_layouts/default/form_errors/default.html
djc/formrenderingtools/templates/form_layouts/default/help_text/default.html
djc/formrenderingtools/templates/form_layouts/default/label/default.html
djc/formrenderingtools/templates/tests/formrenderingtools/as_p_output.html
djc/formrenderingtools/templates/tests/formrenderingtools/as_p_source.html
djc/formrenderingtools/templates/tests/formrenderingtools/as_table_output.html
djc/formrenderingtools/templates/tests/formrenderingtools/as_table_source.html
