Metadata-Version: 1.0
Name: django-formrenderingtools
Version: 0.2.3
Summary: Template-based rendering of Django forms layouts (not widgets).
Home-page: http://bitbucket.org/benoitbryon/django-formrenderingtools
Author: Benoit Bryon
Author-email: benoit@marmelune.net
License: BSD
Download-URL: http://bitbucket.org/benoitbryon/django-formrenderingtools/downloads
Keywords: templates forms layout
Platform: Any
Classifier: Development Status :: 4 - Beta
Classifier: License :: OSI Approved :: BSD License
Classifier: Operating System :: OS Independent
Classifier: Framework :: Django
